odoo/addons/repair_picking/README.rst
odoo/addons/repair_picking/__init__.py
odoo/addons/repair_picking/__manifest__.py
odoo/addons/repair_picking/i18n/it.po
odoo/addons/repair_picking/i18n/repair_picking.pot
odoo/addons/repair_picking/models/__init__.py
odoo/addons/repair_picking/models/repair.py
odoo/addons/repair_picking/models/stock_rule.py
odoo/addons/repair_picking/models/stock_warehouse.py
odoo/addons/repair_picking/readme/CONFIGURE.rst
odoo/addons/repair_picking/readme/CONTRIBUTORS.rst
odoo/addons/repair_picking/readme/DESCRIPTION.rst
odoo/addons/repair_picking/readme/USAGE.rst
odoo/addons/repair_picking/static/description/icon.png
odoo/addons/repair_picking/static/description/index.html
odoo/addons/repair_picking/tests/__init__.py
odoo/addons/repair_picking/tests/test_stock_repair_order.py
odoo/addons/repair_picking/tests/test_stock_repair_warehouse.py
odoo/addons/repair_picking/views/stock_warehouse_views.xml
odoo14_addon_repair_picking-14.0.1.0.2.dev4.dist-info/METADATA
odoo14_addon_repair_picking-14.0.1.0.2.dev4.dist-info/WHEEL
odoo14_addon_repair_picking-14.0.1.0.2.dev4.dist-info/top_level.txt
odoo14_addon_repair_picking-14.0.1.0.2.dev4.dist-info/RECORD
