Metadata-Version: 2.1
Name: odoo14-addon-repair_picking
Version: 14.0.1.0.2.dev4
Summary: Enhanced repair order management with pickings for adding and removing components
Home-page: https://github.com/OCA/manufacture
Author: ForgeFlow, Odoo Community Association (OCA)
Author-email: support@odoo-community.org
License: AGPL-3
Classifier: Programming Language :: Python
Classifier: Framework :: Odoo
Classifier: Framework :: Odoo :: 14.0
Classifier: License :: OSI Approved :: GNU Affero General Public License v3
Requires-Python: >=3.6
Requires-Dist: odoo14-addon-repair-stock
Requires-Dist: odoo14-addon-repair-stock-move
Requires-Dist: odoo14-addon-stock-move-forced-lot
Requires-Dist: odoo<14.1dev,>=14.0a
